color_spec_changer/__init__.py
color_spec_changer/analysis.py
color_spec_changer/constant.py
color_spec_changer/format_.py
color_spec_changer/reference.py
color_spec_changer/translation.py
color_spec_changer/version.py
colorspecchanger-2025.3.dist-info/METADATA
colorspecchanger-2025.3.dist-info/WHEEL
colorspecchanger-2025.3.dist-info/top_level.txt
colorspecchanger-2025.3.dist-info/RECORD
