Metadata-Version: 2.4
Name: ColorSpecChanger
Version: 2025.3
Summary: CsC, the Color Specification Changer
Home-page: https://src.koda.cnrs.fr/eric.debreuve/colorspecchanger/
Author: Eric Debreuve
Author-email: eric.debreuve@cnrs.fr
License: CeCILL-2.1
Project-URL: Documentation, https://src.koda.cnrs.fr/eric.debreuve/colorspecchanger/-/wikis/home
Project-URL: Source, https://src.koda.cnrs.fr/eric.debreuve/colorspecchanger/
Keywords: color,specification,change,translation
Classifier: Topic :: Scientific/Engineering :: Image Processing
Classifier: Intended Audience :: Science/Research
Classifier: License :: OSI Approved :: CEA CNRS Inria Logiciel Libre License, version 2.1 (CeCILL-2.1)
Classifier: Programming Language :: Python :: 3
Classifier: Development Status :: 5 - Production/Stable
Requires-Python: >=3.11
Requires-Dist: numpy
Dynamic: author
Dynamic: author-email
Dynamic: classifier
Dynamic: description
Dynamic: description-content-type
Dynamic: home-page
Dynamic: keywords
Dynamic: license
Dynamic: project-url
Dynamic: requires-dist
Dynamic: requires-python
Dynamic: summary
